{"Logger":{"Runlog":{"SQL":{"Table":"Runlog","Logfile":"sql.log","Database":"cdms_dell","Hostname":"localhost","Password":"","Username":"root","Links BOR":{"Run number":"/Runinfo/Run number","Start time":"/Runinfo/Start time"},"Links EOR":{"Stop time":"/Runinfo/Stop time"},"Write data":false,"Create database":false},"ASCII":{"filename":"runlog.log","Links BOR":{"Run number":"/Runinfo/Run number","Start time":"/Runinfo/Start time"},"Links EOR":{"Stop time":"/Runinfo/Stop time"},"Write data":false}},"History":{"FILE":{"Type":"FILE","Debug":0,"Active":false,"History dir":"","PerVariableHistory":1},"ODBC":{"Type":"ODBC","Debug":0,"Active":false,"Reader_ODBC_DSN":"history_reader","Writer_ODBC_DSN":"history_writer"},"MIDAS":{"Type":"MIDAS","Debug":0,"Active":false,"History dir":"","PerVariableHistory":0},"MYSQL":{"Type":"MYSQL","Debug":0,"Active":true,"MYSQL Reader":"cdms_reader.txt","MYSQL Writer":"cdms_writer.txt"},"SQLITE":{"Type":"SQLITE","Debug":0,"Active":false,"Sqlite dir":"","History dir":""}},"Channels":{"0":{"Settings":{"Type":"Disk","Active":true,"Buffer":"SYSTEM","Format":"MIDAS","Output":"FILE","Compress":"gzip","Event ID":-1,"Filename":".RUN%05d_DUMP%04d.mid","ODB dump":true,"Byte limit":0,"Compression":1,"Event limit":0,"Log messages":"0x00000000","Trigger mask":-1,"Data checksum":"CRC32C","File checksum":"CRC32C","Subdir format":"","Tape capacity":0,"Options Output":["NULL","FILE","FTP","ROOT","PIPE"],"Pbzip2 num cpu":"0x00000000","Pbzip2 options":"","ODB dump format":"xml","Current filename":".RUN00165_DUMP0005.mid.gz","Gzip compression":"0x00000000","Options Compress":["none","gzip","lz4","bzip2","pbzip2"],"Bzip2 compression":"0x00000000","Subrun Byte limit":0,"Pbzip2 compression":"0x00000000","Options Data checksum":["NONE","CRC32C","SHA256","SHA512","ZLIB"],"Options File checksum":["NONE","CRC32C","SHA256","SHA512","ZLIB"],"Options ODB dump format":["odb","xml","json"]},"Statistics":{"Disk level":0.004150041382256053,"Bytes written":354536905,"Files written":22854,"Events written":964,"Bytes written total":17350757541102.0,"Bytes written subrun":15134234,"Bytes written uncompressed":2795275236.0}}},"Data dir":"/home/cdms/packages/SuperCDMS_DAQ/MidasDAQ/online/data/livedata","Elog dir":"/home/cdms/packages/SuperCDMS_DAQ/MidasDAQ/online/elog/","ODB Dump":true,"Write data":true,"History dir":"","Message dir":"","Next subrun":false,"Auto restart":true,"Message file":"midas.log","Run duration":"0x00000000","Tape message":true,"ODB Dump File":"run%05d.json","Subrun duration":"0x0000003c","Watchdog timeout":"0x0000ea60","Async transitions":false,"Auto restart delay":0,"ODB Last Dump File":"last.json","CDMS facility number":24,"Write as CDMS series":true,"Multithread transitions":true,"Message file date format":""},"System":{"Clients":{"2687":{"Host":"cdms-back.cdmsdaq.snolab.ca","Name":"mserver","Server Port":41283,"Hardware type":44},"2689":{"Host":"cdms-back.cdmsdaq.snolab.ca","Name":"Logger","Server Port":45055,"Hardware type":44,"Transition STOP":800,"Transition PAUSE":800,"Transition START":200,"Transition RESUME":200,"Transition STARTABORT":800},"2690":{"Host":"cdms-back.cdmsdaq.snolab.ca","Name":"Sequencer","Server Port":45235,"Hardware type":44},"2691":{"Host":"cdms-back.cdmsdaq.snolab.ca","Name":"mhttpd","Server Port":40335,"Hardware type":44},"2692":{"Host":"cdms-back.cdmsdaq.snolab.ca","Name":"Lazy_0","Server Port":36405,"Hardware type":44,"Transition STOP":810},"346989":{"Host":"cdms-fe1.cdmsdaq.snolab.ca","Name":"DCRCDriverRevF51","Run state":1,"Server Port":36597,"Link timeout":10000,"Hardware type":44,"Transition STOP":500,"Transition PAUSE":500,"Transition START":500,"Transition RESUME":500},"346994":{"RPC":{"17000":true},"Host":"cdms-fe1.cdmsdaq.snolab.ca","Name":"readoutfe_51","Run state":1,"Server Port":41045,"Link timeout":60000,"Hardware type":44,"Transition STOP":500,"Transition PAUSE":500,"Transition START":500,"Transition RESUME":500,"Transition STARTABORT":500},"363523":{"Host":"cdms-fe1.cdmsdaq.snolab.ca","Name":"DCRCDriverRevF50","Run state":1,"Server Port":41027,"Link timeout":10000,"Hardware type":44,"Transition STOP":500,"Transition PAUSE":500,"Transition START":500,"Transition RESUME":500},"363525":{"RPC":{"17000":true},"Host":"cdms-fe1.cdmsdaq.snolab.ca","Name":"readoutfe_50","Run state":1,"Server Port":37383,"Link timeout":60000,"Hardware type":44,"Transition STOP":500,"Transition PAUSE":500,"Transition START":500,"Transition RESUME":500,"Transition STARTABORT":500},"1673892":{"Host":"cdms-fe1.cdmsdaq.snolab.ca","Name":"SDUDriver","Run state":1,"Server Port":45101,"Link timeout":60000,"Hardware type":44,"Transition STOP":500,"Transition PAUSE":500,"Transition START":500,"Transition RESUME":500},"1673893":{"Host":"cdms-fe1.cdmsdaq.snolab.ca","Name":"readoutfe_SDU","Run state":1,"Server Port":41943,"Link timeout":60000,"Hardware type":44,"Transition STOP":500,"Transition PAUSE":500,"Transition START":500,"Transition RESUME":500,"Transition STARTABORT":500},"2768584":{"Host":"cdms-back.cdmsdaq.snolab.ca","Name":"eventbuilder","Run state":1,"Server Port":36209,"Hardware type":44,"Transition STOP":720,"Transition PAUSE":720,"Transition START":[480,100],"Transition RESUME":480,"Transition STARTABORT":720},"3268703":{"Host":"cdms-back.cdmsdaq.snolab.ca","Name":"L2Trigger","Run state":1,"Server Port":34771,"Hardware type":44,"Transition STOP":490,"Transition PAUSE":490,"Transition START":700,"Transition RESUME":700,"Transition STARTABORT":490,"Transition STOP DEFERRED":0}}},"Runinfo":{"State":1,"Stop time":"Wed Sep 10 16:25:30 2025","Run number":165,"Start time":"Wed Sep 10 16:20:14 2025","Online Mode":1,"Start abort":0,"Stop time binary":"0x68c1deba","Start time binary":"0x68c1dd7e","Requested transition":0,"Transition in progress":0},"Equipment":{"EBuilder":{"Special dump numbers":{"Last BORR":-1,"Last EORR":-1,"First BORR":1,"First EORR":-1,"Last BORTS":1,"First BORTS":-1,"First EORTS":-1}}},"Experiment":{"Edit on start":{"Data type":4,"Write data":"/Logger/Write data","Write ODB dump":"/Logger/ODB Dump","Edit Run number":false,"Fridge run number":0}}}